media.py
rst2html5slides.py
rst2html5slides/__init__.py
rst2html5slides/media.py
rst2html5slides/rst2html5slides.py
rst2html5slides/css/slideshow.css
rst2html5slides/js/jquery.min.js
rst2html5slides/js/slide_animations.js
rst2html5slides/js/slideshow.js
rst2html5slides/js/video_animation.js
rst2html5slides/js/greensock/TimelineLite.min.js
rst2html5slides/js/greensock/TimelineMax.min.js
rst2html5slides/js/greensock/TweenLite.min.js
rst2html5slides/js/greensock/TweenMax.min.js
rst2html5slides/js/greensock/jquery.gsap.min.js
rst2html5slides/js/greensock/easing/EasePack.min.js
rst2html5slides/js/greensock/plugins/AttrPlugin.min.js
rst2html5slides/js/greensock/plugins/BezierPlugin.min.js
rst2html5slides/js/greensock/plugins/CSSPlugin.min.js
rst2html5slides/js/greensock/plugins/CSSRulePlugin.min.js
rst2html5slides/js/greensock/plugins/ColorPropsPlugin.min.js
rst2html5slides/js/greensock/plugins/DirectionalRotationPlugin.min.js
rst2html5slides/js/greensock/plugins/EaselPlugin.min.js
rst2html5slides/js/greensock/plugins/EndArrayPlugin.min.js
rst2html5slides/js/greensock/plugins/ModifiersPlugin.min.js
rst2html5slides/js/greensock/plugins/PixiPlugin.min.js
rst2html5slides/js/greensock/plugins/RaphaelPlugin.min.js
rst2html5slides/js/greensock/plugins/RoundPropsPlugin.min.js
rst2html5slides/js/greensock/plugins/ScrollToPlugin.min.js
rst2html5slides/js/greensock/plugins/TextPlugin.min.js
rst2html5slides/js/greensock/utils/Draggable.min.js
rst2html5slides/template/default.html
test/__init__.py
test/cases.py
test/test_output_dir.py
test/test_rst2html5slides.py
rst2html5slides-1.2.2.dist-info/AUTHORS.rst
rst2html5slides-1.2.2.dist-info/LICENSE
rst2html5slides-1.2.2.dist-info/METADATA
rst2html5slides-1.2.2.dist-info/WHEEL
rst2html5slides-1.2.2.dist-info/entry_points.txt
rst2html5slides-1.2.2.dist-info/top_level.txt
rst2html5slides-1.2.2.dist-info/RECORD
