Metadata-Version: 2.1
Name: rst2html5slides
Version: 1.2.2
Summary: rst2html5slides generates a slideshow from a reStructuredText file.
Home-page: UNKNOWN
Author: André Felipe Dias
Author-email: andref.dias@gmail.com
License: MIT License
Keywords: restructuredText,slide,docutils,presentation,html5
Platform: any
Classifier: Development Status :: 4 - Beta
Classifier: Environment :: Console
Classifier: Environment :: Web Environment
Classifier: Intended Audience :: Developers
Classifier: Intended Audience :: Education
Classifier: License :: OSI Approved :: MIT License
Classifier: Operating System :: OS Independent
Classifier: Programming Language :: Python
Classifier: Programming Language :: Python :: 3
Classifier: Topic :: Documentation
Classifier: Topic :: Utilities
Classifier: Topic :: Text Processing :: Markup :: HTML
Requires-Dist: docutils (>=0.14)
Requires-Dist: genshi (>=0.7)
Requires-Dist: micawber (>=0.3.5)
Requires-Dist: rst2html5 (>=1.9.5)
